uvicorn_loguru_integration.py
uvicorn_loguru_integration-0.3.1.dist-info/LICENSE
uvicorn_loguru_integration-0.3.1.dist-info/METADATA
uvicorn_loguru_integration-0.3.1.dist-info/WHEEL
uvicorn_loguru_integration-0.3.1.dist-info/top_level.txt
uvicorn_loguru_integration-0.3.1.dist-info/RECORD
