Metadata-Version: 2.1
Name: uvicorn-loguru-integration
Version: 0.3.1
Summary: Code to integrate uvicorn.run with Loguru logging
Home-page: https://github.com/MatthewScholefield/uvicorn-loguru-integration
Author: Matthew D. Scholefield
Author-email: matthew331199@gmail.com
Keywords: uvicorn loguru integration
Classifier: Development Status :: 3 - Alpha
Classifier: Intended Audience :: Developers
Classifier: Programming Language :: Python :: 3
Classifier: Programming Language :: Python :: 3.4
Classifier: Programming Language :: Python :: 3.5
Classifier: Programming Language :: Python :: 3.6
License-File: LICENSE
Requires-Dist: uvicorn
Requires-Dist: loguru-logging-intercept
